tidydev/__init__.py
tidydev/__main__.py
tidydev/__version__.py
tidydev/analyze.py
tidydev-1.1.0.dist-info/METADATA
tidydev-1.1.0.dist-info/WHEEL
tidydev-1.1.0.dist-info/entry_points.txt
tidydev-1.1.0.dist-info/top_level.txt
tidydev-1.1.0.dist-info/RECORD
