Metadata-Version: 2.1
Name: tidydev
Version: 1.1.0
Summary: Clean up your development directory.
License: Public Domain
Requires-Dist: GitPython
Requires-Dist: tabulate
